fclpy/__init__.py
fclpy/cli.py
fclpy/lispenv.py
fclpy/lispfunc.py
fclpy/lispreader.py
fclpy/lisptype.py
fclpy/runtime.py
fclpy-0.1.0.dist-info/licenses/LICENSE.txt
fclpy-0.1.0.dist-info/METADATA
fclpy-0.1.0.dist-info/WHEEL
fclpy-0.1.0.dist-info/entry_points.txt
fclpy-0.1.0.dist-info/top_level.txt
fclpy-0.1.0.dist-info/RECORD
